{
  "updated_at": "2026-04-29T15:09:25.573257+00:00",
  "scan_seconds": 3.06,
  "scanned_count": 503,
  "both_green": [],
  "both_red": [
    {
      "sym": "WMT",
      "name": "Walmart",
      "mcap": 1011,
      "price": 126.79,
      "basis": 127.05,
      "bxt_today": -1.39,
      "bxt_yest": 2.67,
      "fvb_g": false,
      "fvb_r": true,
      "bxt_g": false,
      "bxt_r": true,
      "ath": 134.69,
      "pct_to_ath": 6.2
    },
    {
      "sym": "PEP",
      "name": "PepsiCo",
      "mcap": 212,
      "price": 154.45,
      "basis": 155.76,
      "bxt_today": -0.31,
      "bxt_yest": 1.55,
      "fvb_g": false,
      "fvb_r": true,
      "bxt_g": false,
      "bxt_r": true,
      "ath": 196.88,
      "pct_to_ath": 27.5
    },
    {
      "sym": "DIS",
      "name": "DIS",
      "mcap": 179,
      "price": 100.96,
      "basis": 101.34,
      "bxt_today": -0.17,
      "bxt_yest": 3.68,
      "fvb_g": false,
      "fvb_r": true,
      "bxt_g": false,
      "bxt_r": true,
      "ath": 203.02,
      "pct_to_ath": 101.1
    },
    {
      "sym": "PH",
      "name": "PH",
      "mcap": 120,
      "price": 952.32,
      "basis": 961.6,
      "bxt_today": -2.88,
      "bxt_yest": 1.03,
      "fvb_g": false,
      "fvb_r": true,
      "bxt_g": false,
      "bxt_r": true,
      "ath": 1034.96,
      "pct_to_ath": 8.7
    },
    {
      "sym": "GM",
      "name": "General Motors",
      "mcap": 69,
      "price": 76.36,
      "basis": 77.28,
      "bxt_today": -0.84,
      "bxt_yest": 6.08,
      "fvb_g": false,
      "fvb_r": true,
      "bxt_g": false,
      "bxt_r": true,
      "ath": 87.62,
      "pct_to_ath": 14.7
    },
    {
      "sym": "HOOD",
      "name": "HOOD",
      "mcap": 64,
      "price": 70.7,
      "basis": 78.82,
      "bxt_today": -4.95,
      "bxt_yest": 6.91,
      "fvb_g": false,
      "fvb_r": true,
      "bxt_g": false,
      "bxt_r": true,
      "ath": 153.86,
      "pct_to_ath": 117.6
    },
    {
      "sym": "GWW",
      "name": "Grainger",
      "mcap": 54,
      "price": 1144.21,
      "basis": 1148.1,
      "bxt_today": -3.09,
      "bxt_yest": 1.21,
      "fvb_g": false,
      "fvb_r": true,
      "bxt_g": false,
      "bxt_r": true,
      "ath": 1227.66,
      "pct_to_ath": 7.3
    },
    {
      "sym": "PSA",
      "name": "PSA",
      "mcap": 52,
      "price": 294.83,
      "basis": 297.39,
      "bxt_today": -3.21,
      "bxt_yest": 2.85,
      "fvb_g": false,
      "fvb_r": true,
      "bxt_g": false,
      "bxt_r": true,
      "ath": 421.76,
      "pct_to_ath": 43.1
    },
    {
      "sym": "TER",
      "name": "TER",
      "mcap": 50,
      "price": 319.88,
      "basis": 362.83,
      "bxt_today": -11.57,
      "bxt_yest": 6.31,
      "fvb_g": false,
      "fvb_r": true,
      "bxt_g": false,
      "bxt_r": true,
      "ath": 422.11,
      "pct_to_ath": 32.0
    },
    {
      "sym": "COIN",
      "name": "COIN",
      "mcap": 47,
      "price": 178.11,
      "basis": 187.39,
      "bxt_today": -2.45,
      "bxt_yest": 5.73,
      "fvb_g": false,
      "fvb_r": true,
      "bxt_g": false,
      "bxt_r": true,
      "ath": 444.65,
      "pct_to_ath": 149.6
    },
    {
      "sym": "CBRE",
      "name": "CBRE",
      "mcap": 42,
      "price": 144.37,
      "basis": 145.12,
      "bxt_today": -0.09,
      "bxt_yest": 5.43,
      "fvb_g": false,
      "fvb_r": true,
      "bxt_g": false,
      "bxt_r": true,
      "ath": 174.27,
      "pct_to_ath": 20.7
    },
    {
      "sym": "MTB",
      "name": "M&T Bank",
      "mcap": 32,
      "price": 215.79,
      "basis": 217.09,
      "bxt_today": -2.17,
      "bxt_yest": 0.72,
      "fvb_g": false,
      "fvb_r": true,
      "bxt_g": false,
      "bxt_r": true,
      "ath": 239.0,
      "pct_to_ath": 10.8
    },
    {
      "sym": "TDY",
      "name": "TDY",
      "mcap": 29,
      "price": 629.56,
      "basis": 642.59,
      "bxt_today": -3.49,
      "bxt_yest": 3.29,
      "fvb_g": false,
      "fvb_r": true,
      "bxt_g": false,
      "bxt_r": true,
      "ath": 693.38,
      "pct_to_ath": 10.1
    }
  ],
  "changes": {
    "green_added": [],
    "green_removed": [],
    "red_added": [],
    "red_removed": [
      {
        "sym": "SPG",
        "name": "SPG",
        "mcap": 76,
        "price": 199.26,
        "basis": 199.31,
        "bxt_today": -2.23,
        "ath": 229.1,
        "pct_to_ath": 15.0
      },
      {
        "sym": "CINF",
        "name": "CINF",
        "mcap": 25,
        "price": 162.63,
        "basis": 163.47,
        "bxt_today": -0.04,
        "ath": 174.27,
        "pct_to_ath": 7.2
      },
      {
        "sym": "DASH",
        "name": "DASH",
        "mcap": 72,
        "price": 164.96,
        "basis": 168.57,
        "bxt_today": -0.05,
        "ath": 285.5,
        "pct_to_ath": 73.1
      }
    ],
    "compared_to": "2026-04-29T15:04:20.771030+00:00"
  }
}